{
  "consumer": {
    "name": "kotsadm-web"
  },
  "provider": {
    "name": "kotsadm-api"
  },
  "interactions": [
    {
      "description": "a query to list clusters for solo account",
      "request": {
        "method": "POST",
        "path": "/graphql",
        "headers": {
          "Authorization": "eyJhbGciOiJIUzI1NiIsInR5cCI6IkpXVCJ9.eyJpYXQiOjE1NDYzMDQ0MDAwMDAsInRva2VuIjoibm90LWNoZWNrZWQiLCJzZXNzaW9uSWQiOiJzb2xvLWFjY291bnQtc2Vzc2lvbi0xIn0.pC3xMQDD5zseVcOVzypZkC9ZyngBoT_nLymZTbJTHdA",
          "Content-Type": "application/json"
        },
        "body": {
          "operationName": "listClusters",
          "query": "\n  query listClusters {\n    listClusters {\n      id\n      title\n      slug\n      createdOn\n      lastUpdated\n      shipOpsRef {\n        token\n      }\n      totalApplicationCount\n    }\n  }\n",
          "variables": {
          }
        },
        "matchingRules": {
          "$.body.query": {
            "match": "regex",
            "regex": "\\s*query\\s*listClusters\\s*\\{\\s*listClusters\\s*\\{\\s*id\\s*title\\s*slug\\s*createdOn\\s*lastUpdated\\s*shipOpsRef\\s*\\{\\s*token\\s*\\}\\s*totalApplicationCount\\s*\\}\\s*\\}\\s*"
          }
        }
      },
      "response": {
        "status": 200,
        "headers": {
          "Content-Type": "application/json"
        },
        "body": {
          "data": {
            "listClusters": [
              {
                "id": "solo-account-cluster-1",
                "title": "Solo Cluster",
                "slug": "solo-cluster",
                "totalApplicationCount": 1,
                "createdOn": "2019-04-10 12:34:56.789",
                "lastUpdated": "2019-04-11 01:23:45.567",
                "shipOpsRef": {
                  "token": "solo-account-cluster-token"
                }
              },
              {
                "id": "solo-account-cluster-2",
                "title": "Solo GitHub Cluster",
                "slug": "solo-cluster-2",
                "totalApplicationCount": 0,
                "createdOn": "2019-04-10 12:34:56.789",
                "lastUpdated": "2019-04-11 01:23:45.567",
                "shipOpsRef": null
              },
              {
                "id": "l9cpydvcf30ekf25pmokwn6qlnxscrci",
                "title": "this-cluster",
                "slug": "this-cluster",
                "createdOn": "Wed Jan 22 2020 00:34:12 GMT+0000 (Coordinated Universal Time)",
                "lastUpdated": null,
                "shipOpsRef": {
                  "token": "g7yoarinjpaft3si5z1h5de1uam443bb"
                },
                "totalApplicationCount": 0
              }
            ]
          }
        },
        "matchingRules": {
          "$.body.data.listClusters[0].createdOn": {
            "match": "type"
          },
          "$.body.data.listClusters[0].lastUpdated": {
            "match": "type"
          },
          "$.body.data.listClusters[1].createdOn": {
            "match": "type"
          },
          "$.body.data.listClusters[1].lastUpdated": {
            "match": "type"
          },
          "$.body.data.listClusters[2].id": {
            "match": "type"
          },
          "$.body.data.listClusters[2].createdOn": {
            "match": "type"
          },
          "$.body.data.listClusters[2].shipOpsRef.token": {
            "match": "type"
          }
        }
      }
    },
    {
      "description": "A query to get a kots app",
      "request": {
        "method": "POST",
        "path": "/graphql",
        "headers": {
          "Authorization": "eyJhbGciOiJIUzI1NiIsInR5cCI6IkpXVCJ9.eyJpYXQiOjE1NDYzMDQ0MDAwMDAsInRva2VuIjoibm90LWNoZWNrZWQiLCJzZXNzaW9uSWQiOiJnZXQta290cy1hcHAtdXNlci1zZXNzaW9uIn0.2zd4bH-mpHwEOwkp4JW1l_tOR5J36IfcyxfAvLxe8WE",
          "Content-Type": "application/json"
        },
        "body": {
          "operationName": "getKotsApp",
          "query": "\n  query getKotsApp($slug: String!) {\n    getKotsApp(slug: $slug) {\n      id\n      name\n      iconUri\n      createdAt\n      updatedAt\n      slug\n      upstreamUri\n      currentSequence\n      hasPreflight\n      isAirgap\n      isConfigurable\n      isGitOpsSupported\n      allowRollback\n      isSnapshotSupported\n      currentVersion {\n        title\n        status\n        createdOn\n        sequence\n        releaseNotes\n        deployedAt\n      }\n      lastUpdateCheckAt\n      bundleCommand\n      downstreams {\n        name\n        links {\n          title\n          uri\n        }\n        currentVersion {\n          title\n          status\n          createdOn\n          sequence\n          deployedAt\n          source\n          releaseNotes\n          parentSequence\n        }\n        pendingVersions {\n          title\n          status\n          createdOn\n          sequence\n          deployedAt\n          parentSequence\n        }\n        pastVersions {\n          title\n          status\n          createdOn\n          sequence\n          deployedAt\n          parentSequence\n        }\n        gitops {\n          enabled\n          provider\n          uri\n          hostname\n          path\n          branch\n          format\n          action\n          deployKey\n          isConnected\n        }\n        cluster {\n          id\n          title\n          slug\n          createdOn\n          lastUpdated\n          currentVersion {\n            title\n            status\n            createdOn\n            sequence\n            deployedAt\n          }\n          shipOpsRef {\n            token\n          }\n          totalApplicationCount\n        }\n      }\n    }\n  }\n",
          "variables": {
            "slug": "kots-app-slug"
          }
        },
        "matchingRules": {
          "$.body.query": {
            "match": "regex",
            "regex": "\\s*query\\s*getKotsApp\\(\\$slug:\\s*String!\\)\\s*\\{\\s*getKotsApp\\(slug:\\s*\\$slug\\)\\s*\\{\\s*id\\s*name\\s*iconUri\\s*createdAt\\s*updatedAt\\s*slug\\s*upstreamUri\\s*currentSequence\\s*hasPreflight\\s*isAirgap\\s*isConfigurable\\s*isGitOpsSupported\\s*allowRollback\\s*isSnapshotSupported\\s*currentVersion\\s*\\{\\s*title\\s*status\\s*createdOn\\s*sequence\\s*releaseNotes\\s*deployedAt\\s*\\}\\s*lastUpdateCheckAt\\s*bundleCommand\\s*downstreams\\s*\\{\\s*name\\s*links\\s*\\{\\s*title\\s*uri\\s*\\}\\s*currentVersion\\s*\\{\\s*title\\s*status\\s*createdOn\\s*sequence\\s*deployedAt\\s*source\\s*releaseNotes\\s*parentSequence\\s*\\}\\s*pendingVersions\\s*\\{\\s*title\\s*status\\s*createdOn\\s*sequence\\s*deployedAt\\s*parentSequence\\s*\\}\\s*pastVersions\\s*\\{\\s*title\\s*status\\s*createdOn\\s*sequence\\s*deployedAt\\s*parentSequence\\s*\\}\\s*gitops\\s*\\{\\s*enabled\\s*provider\\s*uri\\s*hostname\\s*path\\s*branch\\s*format\\s*action\\s*deployKey\\s*isConnected\\s*\\}\\s*cluster\\s*\\{\\s*id\\s*title\\s*slug\\s*createdOn\\s*lastUpdated\\s*currentVersion\\s*\\{\\s*title\\s*status\\s*createdOn\\s*sequence\\s*deployedAt\\s*\\}\\s*shipOpsRef\\s*\\{\\s*token\\s*\\}\\s*totalApplicationCount\\s*\\}\\s*\\}\\s*\\}\\s*\\}\\s*"
          }
        }
      },
      "response": {
        "status": 200,
        "headers": {
          "Content-Type": "application/json"
        },
        "body": {
          "data": {
            "getKotsApp": {
              "id": "get-kots-app-id",
              "name": "kots-app-name",
              "createdAt": "date",
              "updatedAt": "date",
              "slug": "kots-app-slug",
              "currentSequence": 0,
              "hasPreflight": false,
              "isAirgap": false,
              "currentVersion": null,
              "lastUpdateCheckAt": "date",
              "bundleCommand": "\n      curl https://krew.sh/support-bundle | bash\n      kubectl support-bundle undefined/api/v1/troubleshoot/kots-app-slug\n    ",
              "downstreams": [

              ]
            }
          }
        },
        "matchingRules": {
          "$.body.data.getKotsApp.createdAt": {
            "match": "type"
          },
          "$.body.data.getKotsApp.updatedAt": {
            "match": "type"
          },
          "$.body.data.getKotsApp.lastUpdateCheckAt": {
            "match": "type"
          }
        }
      }
    },
    {
      "description": "a query to get a kots preflight result",
      "request": {
        "method": "POST",
        "path": "/graphql",
        "headers": {
          "Authorization": "eyJhbGciOiJIUzI1NiIsInR5cCI6IkpXVCJ9.eyJpYXQiOjE1NDYzMDQ0MDAwMDAsInRva2VuIjoibm90LWNoZWNrZWQiLCJzZXNzaW9uSWQiOiJnZXQta290cy1wcmVmbGlnaHQtcmVzdWx0LXVzZXItc2Vzc2lvbiJ9.IhYlfTOPveT0BNlzkZUhFbO32Zq0wg8wbwgdegtizPc",
          "Content-Type": "application/json"
        },
        "body": {
          "operationName": "getKotsPreflightResult",
          "query": "\n  query getKotsPreflightResult($appSlug: String!, $clusterSlug: String!, $sequence: Int!) {\n    getKotsPreflightResult(appSlug: $appSlug, clusterSlug: $clusterSlug, sequence: $sequence) {\n      appSlug\n      clusterSlug\n      result\n      createdAt\n    }\n  }\n",
          "variables": {
            "appSlug": "get-kots-preflight-result-app-slug",
            "clusterSlug": "get-kots-preflight-result-cluster-slug",
            "sequence": 0
          }
        },
        "matchingRules": {
          "$.body.query": {
            "match": "regex",
            "regex": "\\s*query\\s*getKotsPreflightResult\\(\\$appSlug:\\s*String!,\\s*\\$clusterSlug:\\s*String!,\\s*\\$sequence:\\s*Int!\\)\\s*\\{\\s*getKotsPreflightResult\\(appSlug:\\s*\\$appSlug,\\s*clusterSlug:\\s*\\$clusterSlug,\\s*sequence:\\s*\\$sequence\\)\\s*\\{\\s*appSlug\\s*clusterSlug\\s*result\\s*createdAt\\s*\\}\\s*\\}\\s*"
          }
        }
      },
      "response": {
        "status": 200,
        "headers": {
          "Content-Type": "application/json"
        },
        "body": {
          "data": {
            "getKotsPreflightResult": {
              "appSlug": "get-kots-preflight-result-app-slug",
              "clusterSlug": "get-kots-preflight-result-cluster-slug",
              "result": "JSONString",
              "createdAt": "date"
            }
          }
        },
        "matchingRules": {
          "$.body.data.getKotsPreflightResult.result": {
            "match": "type"
          },
          "$.body.data.getKotsPreflightResult.createdAt": {
            "match": "type"
          }
        }
      }
    },
    {
      "description": "a query to get the latest kots preflight result",
      "request": {
        "method": "POST",
        "path": "/graphql",
        "headers": {
          "Authorization": "eyJhbGciOiJIUzI1NiIsInR5cCI6IkpXVCJ9.eyJpYXQiOjE1NDYzMDQ0MDAwMDAsInRva2VuIjoibm90LWNoZWNrZWQiLCJzZXNzaW9uSWQiOiJnZXQtbGF0ZXN0LWtvdHMtcHJlZmxpZ2h0LXJlc3VsdC11c2VyLXNlc3Npb24ifQ.slbB1d3nuhQUlEYWbbQf6yf5NnnMQG1DHSh_aydIPSI",
          "Content-Type": "application/json"
        },
        "body": {
          "operationName": "getLatestKotsPreflightResult",
          "query": "\n  query getLatestKotsPreflightResult {\n    getLatestKotsPreflightResult {\n      appSlug\n      clusterSlug\n      result\n      createdAt\n    }\n  }\n",
          "variables": {
          }
        },
        "matchingRules": {
          "$.body.query": {
            "match": "regex",
            "regex": "\\s*query\\s*getLatestKotsPreflightResult\\s*\\{\\s*getLatestKotsPreflightResult\\s*\\{\\s*appSlug\\s*clusterSlug\\s*result\\s*createdAt\\s*\\}\\s*\\}\\s*"
          }
        }
      },
      "response": {
        "status": 200,
        "headers": {
          "Content-Type": "application/json"
        },
        "body": {
          "data": {
            "getLatestKotsPreflightResult": {
              "appSlug": "get-latest-kots-preflight-result-app-slug",
              "clusterSlug": "get-latest-kots-preflight-result-cluster-slug",
              "result": "JSONString",
              "createdAt": "date"
            }
          }
        },
        "matchingRules": {
          "$.body.data.getLatestKotsPreflightResult.result": {
            "match": "type"
          },
          "$.body.data.getLatestKotsPreflightResult.createdAt": {
            "match": "type"
          }
        }
      }
    },
    {
      "description": "a mutation to deploy a kots version",
      "request": {
        "method": "POST",
        "path": "/graphql",
        "headers": {
          "Authorization": "eyJhbGciOiJIUzI1NiIsInR5cCI6IkpXVCJ9.eyJpYXQiOjE1NDYzMDQ0MDAwMDAsInRva2VuIjoibm90LWNoZWNrZWQiLCJzZXNzaW9uSWQiOiJkZXBsb3kta290cy12ZXJzaW9uLXVzZXItc2Vzc2lvbiJ9.pLpB0KiQvda0NeN79dNGIGjePpEEmcFmSJuDhq7rAl0",
          "Content-Type": "application/json"
        },
        "body": {
          "operationName": "deployKotsVersion",
          "query": "\n  mutation deployKotsVersion($upstreamSlug: String!, $sequence: Int!, $clusterSlug: String!) {\n    deployKotsVersion(upstreamSlug: $upstreamSlug, sequence: $sequence, clusterSlug: $clusterSlug)\n  }\n",
          "variables": {
            "upstreamSlug": "deploy-kots-version-app-slug",
            "sequence": 1,
            "clusterSlug": "deploy-kots-version-cluster-slug"
          }
        },
        "matchingRules": {
          "$.body.query": {
            "match": "regex",
            "regex": "\\s*mutation\\s*deployKotsVersion\\(\\$upstreamSlug:\\s*String!,\\s*\\$sequence:\\s*Int!,\\s*\\$clusterSlug:\\s*String!\\)\\s*\\{\\s*deployKotsVersion\\(upstreamSlug:\\s*\\$upstreamSlug,\\s*sequence:\\s*\\$sequence,\\s*clusterSlug:\\s*\\$clusterSlug\\)\\s*\\}\\s*"
          }
        }
      },
      "response": {
        "status": 200,
        "headers": {
          "Content-Type": "application/json"
        },
        "body": {
          "data": {
            "deployKotsVersion": true
          }
        }
      }
    },
    {
      "description": "A query to get kots downstream version history",
      "request": {
        "method": "POST",
        "path": "/graphql",
        "headers": {
          "Authorization": "eyJhbGciOiJIUzI1NiIsInR5cCI6IkpXVCJ9.eyJpYXQiOjE1NDYzMDQ0MDAwMDAsInRva2VuIjoibm90LWNoZWNrZWQiLCJzZXNzaW9uSWQiOiJnZXQta290cy1kb3duc3RyZWFtLWhpc3RvcnktdXNlci1zZXNzaW9uIn0.uTMgysq4P9JCZevP4XMN611ji5CFnsznhJviXFjW4I8",
          "Content-Type": "application/json"
        },
        "body": {
          "operationName": "getKotsDownstreamHistory",
          "query": "\n  query getKotsDownstreamHistory($clusterSlug: String!, $upstreamSlug: String!) {\n    getKotsDownstreamHistory(clusterSlug: $clusterSlug, upstreamSlug: $upstreamSlug) {\n      title\n      status\n      createdOn\n      sequence\n      parentSequence\n      releaseNotes\n      deployedAt\n      source\n      diffSummary\n      preflightResult\n      preflightResultCreatedAt\n      commitUrl\n      gitDeployable\n    }\n  }\n",
          "variables": {
            "clusterSlug": "get-kots-downstream-history-cluster-slug",
            "upstreamSlug": "get-kots-downstream-history-app-slug"
          }
        },
        "matchingRules": {
          "$.body.query": {
            "match": "regex",
            "regex": "\\s*query\\s*getKotsDownstreamHistory\\(\\$clusterSlug:\\s*String!,\\s*\\$upstreamSlug:\\s*String!\\)\\s*\\{\\s*getKotsDownstreamHistory\\(clusterSlug:\\s*\\$clusterSlug,\\s*upstreamSlug:\\s*\\$upstreamSlug\\)\\s*\\{\\s*title\\s*status\\s*createdOn\\s*sequence\\s*parentSequence\\s*releaseNotes\\s*deployedAt\\s*source\\s*diffSummary\\s*preflightResult\\s*preflightResultCreatedAt\\s*commitUrl\\s*gitDeployable\\s*\\}\\s*\\}\\s*"
          }
        }
      },
      "response": {
        "status": 200,
        "headers": {
          "Content-Type": "application/json"
        },
        "body": {
          "data": {
            "getKotsDownstreamHistory": [
              {
                "title": "my-awesome-version",
                "status": "pending",
                "createdOn": "date",
                "sequence": 0,
                "deployedAt": "date",
                "preflightResult": "JSONPreflightResult",
                "preflightResultCreatedAt": "date"
              }
            ]
          }
        },
        "matchingRules": {
          "$.body.data.getKotsDownstreamHistory[0].createdOn": {
            "match": "type"
          },
          "$.body.data.getKotsDownstreamHistory[0].deployedAt": {
            "match": "type"
          },
          "$.body.data.getKotsDownstreamHistory[0].preflightResult": {
            "match": "type"
          },
          "$.body.data.getKotsDownstreamHistory[0].preflightResultCreatedAt": {
            "match": "type"
          }
        }
      }
    },
    {
      "description": "A query to get kots downstream version history that has release notes",
      "request": {
        "method": "POST",
        "path": "/graphql",
        "headers": {
          "Authorization": "eyJhbGciOiJIUzI1NiIsInR5cCI6IkpXVCJ9.eyJpYXQiOjE1NDYzMDQ0MDAwMDAsInRva2VuIjoibm90LWNoZWNrZWQiLCJzZXNzaW9uSWQiOiJrb3RzLXJlbGVhc2Utbm90ZXMtdXNlci1zZXNzaW9uIn0.etnIn-jtkBXBViCV6qFXos_3DrC4AuZr5wBZppqhjPk",
          "Content-Type": "application/json"
        },
        "body": {
          "operationName": "getKotsDownstreamHistory",
          "query": "\n  query getKotsDownstreamHistory($clusterSlug: String!, $upstreamSlug: String!) {\n    getKotsDownstreamHistory(clusterSlug: $clusterSlug, upstreamSlug: $upstreamSlug) {\n      title\n      status\n      createdOn\n      sequence\n      parentSequence\n      releaseNotes\n      deployedAt\n      source\n      diffSummary\n      preflightResult\n      preflightResultCreatedAt\n      commitUrl\n      gitDeployable\n    }\n  }\n",
          "variables": {
            "clusterSlug": "kots-release-notes-cluster-slug",
            "upstreamSlug": "kots-release-notes-app-slug"
          }
        },
        "matchingRules": {
          "$.body.query": {
            "match": "regex",
            "regex": "\\s*query\\s*getKotsDownstreamHistory\\(\\$clusterSlug:\\s*String!,\\s*\\$upstreamSlug:\\s*String!\\)\\s*\\{\\s*getKotsDownstreamHistory\\(clusterSlug:\\s*\\$clusterSlug,\\s*upstreamSlug:\\s*\\$upstreamSlug\\)\\s*\\{\\s*title\\s*status\\s*createdOn\\s*sequence\\s*parentSequence\\s*releaseNotes\\s*deployedAt\\s*source\\s*diffSummary\\s*preflightResult\\s*preflightResultCreatedAt\\s*commitUrl\\s*gitDeployable\\s*\\}\\s*\\}\\s*"
          }
        }
      },
      "response": {
        "status": 200,
        "headers": {
          "Content-Type": "application/json"
        },
        "body": {
          "data": {
            "getKotsDownstreamHistory": [
              {
                "title": "my-other-awesome-version",
                "status": "pending",
                "createdOn": "Fri Apr 19 2019 01:23:45 GMT+0000 (Coordinated Universal Time)",
                "sequence": 0,
                "releaseNotes": "# Release Notes Markdown Text",
                "deployedAt": "Fri Apr 19 2019 01:23:45 GMT+0000 (Coordinated Universal Time)",
                "preflightResult": "string",
                "preflightResultCreatedAt": "Fri Apr 19 2019 01:23:45 GMT+0000 (Coordinated Universal Time)"
              }
            ]
          }
        },
        "matchingRules": {
          "$.body.data.getKotsDownstreamHistory[0].createdOn": {
            "match": "type"
          },
          "$.body.data.getKotsDownstreamHistory[0].deployedAt": {
            "match": "type"
          },
          "$.body.data.getKotsDownstreamHistory[0].preflightResult": {
            "match": "type"
          },
          "$.body.data.getKotsDownstreamHistory[0].preflightResultCreatedAt": {
            "match": "type"
          }
        }
      }
    },
    {
      "description": "A query to get kots downstream version history without release notes",
      "request": {
        "method": "POST",
        "path": "/graphql",
        "headers": {
          "Authorization": "eyJhbGciOiJIUzI1NiIsInR5cCI6IkpXVCJ9.eyJpYXQiOjE1NDYzMDQ0MDAwMDAsInRva2VuIjoibm90LWNoZWNrZWQiLCJzZXNzaW9uSWQiOiJrb3RzLW5vLXJlbGVhc2Utbm90ZXMtdXNlci1zZXNzaW9uIn0.eNvGKY0UU2lIXWv-NwmLLJxXFhVGY041ohDu3fKVkZU",
          "Content-Type": "application/json"
        },
        "body": {
          "operationName": "getKotsDownstreamHistory",
          "query": "\n  query getKotsDownstreamHistory($clusterSlug: String!, $upstreamSlug: String!) {\n    getKotsDownstreamHistory(clusterSlug: $clusterSlug, upstreamSlug: $upstreamSlug) {\n      title\n      status\n      createdOn\n      sequence\n      parentSequence\n      releaseNotes\n      deployedAt\n      source\n      diffSummary\n      preflightResult\n      preflightResultCreatedAt\n      commitUrl\n      gitDeployable\n    }\n  }\n",
          "variables": {
            "clusterSlug": "kots-no-release-notes-cluster-slug",
            "upstreamSlug": "kots-no-release-notes-app-slug"
          }
        },
        "matchingRules": {
          "$.body.query": {
            "match": "regex",
            "regex": "\\s*query\\s*getKotsDownstreamHistory\\(\\$clusterSlug:\\s*String!,\\s*\\$upstreamSlug:\\s*String!\\)\\s*\\{\\s*getKotsDownstreamHistory\\(clusterSlug:\\s*\\$clusterSlug,\\s*upstreamSlug:\\s*\\$upstreamSlug\\)\\s*\\{\\s*title\\s*status\\s*createdOn\\s*sequence\\s*parentSequence\\s*releaseNotes\\s*deployedAt\\s*source\\s*diffSummary\\s*preflightResult\\s*preflightResultCreatedAt\\s*commitUrl\\s*gitDeployable\\s*\\}\\s*\\}\\s*"
          }
        }
      },
      "response": {
        "status": 200,
        "headers": {
          "Content-Type": "application/json"
        },
        "body": {
          "data": {
            "getKotsDownstreamHistory": [
              {
                "title": "kots-no-release-notes-version-label",
                "status": "pending",
                "createdOn": "Fri Apr 19 2019 01:23:45 GMT+0000 (Coordinated Universal Time)",
                "sequence": 0,
                "releaseNotes": "",
                "deployedAt": "Fri Apr 19 2019 01:23:45 GMT+0000 (Coordinated Universal Time)",
                "preflightResult": null,
                "preflightResultCreatedAt": null
              }
            ]
          }
        },
        "matchingRules": {
          "$.body.data.getKotsDownstreamHistory[0].createdOn": {
            "match": "type"
          },
          "$.body.data.getKotsDownstreamHistory[0].deployedAt": {
            "match": "type"
          }
        }
      }
    },
    {
      "description": "A query to get downstream version history for a kots app that has different midstream sequence than the downstream",
      "request": {
        "method": "POST",
        "path": "/graphql",
        "headers": {
          "Authorization": "eyJhbGciOiJIUzI1NiIsInR5cCI6IkpXVCJ9.eyJpYXQiOjE1NDYzMDQ0MDAwMDAsInRva2VuIjoibm90LWNoZWNrZWQiLCJzZXNzaW9uSWQiOiJrb3RzLWRpZmZlcmVudC1zZXF1ZW5jZS11c2VyLXNlc3Npb24ifQ.SpkETRRfF-KcCEcOqREWO1hrKsW2Y6O-JP7eopTX0pM",
          "Content-Type": "application/json"
        },
        "body": {
          "operationName": "getKotsDownstreamHistory",
          "query": "\n  query getKotsDownstreamHistory($clusterSlug: String!, $upstreamSlug: String!) {\n    getKotsDownstreamHistory(clusterSlug: $clusterSlug, upstreamSlug: $upstreamSlug) {\n      title\n      status\n      createdOn\n      sequence\n      parentSequence\n      releaseNotes\n      deployedAt\n      source\n      diffSummary\n      preflightResult\n      preflightResultCreatedAt\n      commitUrl\n      gitDeployable\n    }\n  }\n",
          "variables": {
            "clusterSlug": "kots-different-sequence-cluster-slug",
            "upstreamSlug": "kots-different-sequence-app-slug"
          }
        },
        "matchingRules": {
          "$.body.query": {
            "match": "regex",
            "regex": "\\s*query\\s*getKotsDownstreamHistory\\(\\$clusterSlug:\\s*String!,\\s*\\$upstreamSlug:\\s*String!\\)\\s*\\{\\s*getKotsDownstreamHistory\\(clusterSlug:\\s*\\$clusterSlug,\\s*upstreamSlug:\\s*\\$upstreamSlug\\)\\s*\\{\\s*title\\s*status\\s*createdOn\\s*sequence\\s*parentSequence\\s*releaseNotes\\s*deployedAt\\s*source\\s*diffSummary\\s*preflightResult\\s*preflightResultCreatedAt\\s*commitUrl\\s*gitDeployable\\s*\\}\\s*\\}\\s*"
          }
        }
      },
      "response": {
        "status": 200,
        "headers": {
          "Content-Type": "application/json"
        },
        "body": {
          "data": {
            "getKotsDownstreamHistory": [
              {
                "title": "my-other-awesome-version-2",
                "status": "deploying",
                "createdOn": "Fri Apr 19 2019 01:23:45 GMT+0000 (Coordinated Universal Time)",
                "sequence": 1,
                "releaseNotes": "# Markdown string here",
                "deployedAt": "Fri Apr 19 2019 01:23:45 GMT+0000 (Coordinated Universal Time)",
                "preflightResult": "string",
                "preflightResultCreatedAt": "Fri Apr 19 2019 01:23:45 GMT+0000 (Coordinated Universal Time)"
              },
              {
                "title": "my-other-awesome-version",
                "status": "deploying",
                "createdOn": "Fri Apr 19 2019 01:23:45 GMT+0000 (Coordinated Universal Time)",
                "sequence": 0,
                "releaseNotes": "# Markdown string here",
                "deployedAt": "Fri Apr 19 2019 01:23:45 GMT+0000 (Coordinated Universal Time)",
                "preflightResult": "string",
                "preflightResultCreatedAt": "Fri Apr 19 2019 01:23:45 GMT+0000 (Coordinated Universal Time)"
              }
            ]
          }
        },
        "matchingRules": {
          "$.body.data.getKotsDownstreamHistory[0].createdOn": {
            "match": "type"
          },
          "$.body.data.getKotsDownstreamHistory[0].deployedAt": {
            "match": "type"
          },
          "$.body.data.getKotsDownstreamHistory[0].preflightResult": {
            "match": "type"
          },
          "$.body.data.getKotsDownstreamHistory[0].preflightResultCreatedAt": {
            "match": "type"
          },
          "$.body.data.getKotsDownstreamHistory[1].createdOn": {
            "match": "type"
          },
          "$.body.data.getKotsDownstreamHistory[1].deployedAt": {
            "match": "type"
          },
          "$.body.data.getKotsDownstreamHistory[1].preflightResult": {
            "match": "type"
          },
          "$.body.data.getKotsDownstreamHistory[1].preflightResultCreatedAt": {
            "match": "type"
          }
        }
      }
    }
  ],
  "metadata": {
    "pactSpecification": {
      "version": "2.0.0"
    }
  }
}